{
  "users": [
    { "id": 1, "firstName": "Jesselyn", "lastName": "Sivess", "age": 72 },
    { "id": 2, "firstName": "Hedwiga", "lastName": "Nesbitt", "age": 35 },
    { "id": 3, "firstName": "Kasper", "lastName": "Ferrarini", "age": 45 },
    { "id": 4, "firstName": "Kira", "lastName": "Well", "age": 34 },
    { "id": 5, "firstName": "Lettie", "lastName": "Buckthorpe", "age": 75 },
    { "id": 6, "firstName": "Arlene", "lastName": "Scothern", "age": 68 },
    { "id": 7, "firstName": "Susanna", "lastName": "Vankov", "age": 26 },
    { "id": 8, "firstName": "Kris", "lastName": "Wheatman", "age": 52 },
    { "id": 9, "firstName": "Roger", "lastName": "O'Doghesty", "age": 30 },
    { "id": 10, "firstName": "Fremont", "lastName": "Schrinel", "age": 70 },
    { "id": 11, "firstName": "Debera", "lastName": "Peagrim", "age": 69 },
    { "id": 12, "firstName": "Nicholas", "lastName": "Benneyworth", "age": 55 },
    { "id": 13, "firstName": "Rey", "lastName": "Copes", "age": 81 },
    { "id": 14, "firstName": "Nicol", "lastName": "Skedge", "age": 52 },
    { "id": 15, "firstName": "Marilin", "lastName": "Choppin", "age": 73 },
    { "id": 16, "firstName": "Myrta", "lastName": "Goch", "age": 76 },
    { "id": 17, "firstName": "Claudia", "lastName": "Guiet", "age": 38 },
    { "id": 18, "firstName": "Teriann", "lastName": "Kelmere", "age": 45 },
    { "id": 19, "firstName": "Ario", "lastName": "Cassimer", "age": 59 },
    { "id": 20, "firstName": "Ranee", "lastName": "Hegg", "age": 62 },
    { "id": 21, "firstName": "Adeline", "lastName": "Loveday", "age": 26 },
    { "id": 22, "firstName": "Lorne", "lastName": "Rippin", "age": 35 },
    { "id": 23, "firstName": "Nonna", "lastName": "Partner", "age": 60 },
    { "id": 24, "firstName": "Ripley", "lastName": "Andriessen", "age": 37 },
    { "id": 25, "firstName": "Zack", "lastName": "Fackrell", "age": 49 },
    { "id": 26, "firstName": "Alyss", "lastName": "Vannucci", "age": 37 },
    { "id": 27, "firstName": "Claudetta", "lastName": "Moston", "age": 18 },
    { "id": 28, "firstName": "Rafaela", "lastName": "Damerell", "age": 65 },
    { "id": 29, "firstName": "Oralle", "lastName": "Yarn", "age": 59 },
    { "id": 30, "firstName": "Coralyn", "lastName": "Donson", "age": 24 },
    { "id": 31, "firstName": "Hildegaard", "lastName": "Legan", "age": 33 },
    { "id": 32, "firstName": "Wilma", "lastName": "Ashmore", "age": 19 },
    { "id": 33, "firstName": "Gordan", "lastName": "Hartford", "age": 49 },
    { "id": 34, "firstName": "Roda", "lastName": "Mongeot", "age": 76 },
    { "id": 35, "firstName": "Andree", "lastName": "Marsden", "age": 26 },
    {
      "id": 36,
      "firstName": "Shurlocke",
      "lastName": "Schleswig-Holstein",
      "age": 27
    },
    { "id": 37, "firstName": "Catarina", "lastName": "Bedo", "age": 87 },
    { "id": 38, "firstName": "Delilah", "lastName": "Chafney", "age": 63 },
    { "id": 39, "firstName": "Blanca", "lastName": "Gleadhall", "age": 36 },
    { "id": 40, "firstName": "Elwyn", "lastName": "Ingarfield", "age": 73 },
    { "id": 41, "firstName": "Ricki", "lastName": "Heindrich", "age": 58 },
    { "id": 42, "firstName": "Desiri", "lastName": "De Robertis", "age": 43 },
    { "id": 43, "firstName": "Florrie", "lastName": "Stranio", "age": 26 },
    { "id": 44, "firstName": "Vanya", "lastName": "Cello", "age": 40 },
    { "id": 45, "firstName": "Kim", "lastName": "Raison", "age": 48 },
    { "id": 46, "firstName": "Verge", "lastName": "Hun", "age": 28 },
    { "id": 47, "firstName": "Joyan", "lastName": "Gittings", "age": 45 },
    { "id": 48, "firstName": "Katie", "lastName": "Moscon", "age": 59 },
    { "id": 49, "firstName": "Mozes", "lastName": "Gentery", "age": 79 },
    { "id": 50, "firstName": "Charissa", "lastName": "Peplay", "age": 87 },
    { "id": 51, "firstName": "Mendie", "lastName": "Albrook", "age": 74 },
    { "id": 52, "firstName": "Bert", "lastName": "Faithfull", "age": 24 },
    { "id": 53, "firstName": "Kristien", "lastName": "Tennison", "age": 35 },
    { "id": 54, "firstName": "Zonnya", "lastName": "Peeke", "age": 78 },
    { "id": 55, "firstName": "Alfredo", "lastName": "Middiff", "age": 69 },
    { "id": 56, "firstName": "Erica", "lastName": "Willford", "age": 17 },
    { "id": 57, "firstName": "Milo", "lastName": "Rain", "age": 45 },
    { "id": 58, "firstName": "Virgie", "lastName": "Slamaker", "age": 42 },
    { "id": 59, "firstName": "Amalle", "lastName": "Dowsing", "age": 27 },
    { "id": 60, "firstName": "Roderigo", "lastName": "Owbrick", "age": 19 },
    { "id": 61, "firstName": "Evonne", "lastName": "Tattershall", "age": 55 },
    { "id": 62, "firstName": "Ellwood", "lastName": "Sambedge", "age": 57 },
    { "id": 63, "firstName": "Nikolai", "lastName": "Charer", "age": 17 },
    { "id": 64, "firstName": "Carlita", "lastName": "Pycock", "age": 68 },
    { "id": 65, "firstName": "Muire", "lastName": "Doret", "age": 20 },
    { "id": 66, "firstName": "Allyson", "lastName": "Romi", "age": 25 },
    { "id": 67, "firstName": "Bing", "lastName": "Orcas", "age": 17 },
    { "id": 68, "firstName": "Nichole", "lastName": "Pierpoint", "age": 86 },
    { "id": 69, "firstName": "Darleen", "lastName": "Easterbrook", "age": 22 },
    { "id": 70, "firstName": "Dominga", "lastName": "Fozard", "age": 78 },
    { "id": 71, "firstName": "Jackquelin", "lastName": "Dahmke", "age": 32 },
    { "id": 72, "firstName": "Tammie", "lastName": "Tasseler", "age": 31 },
    { "id": 73, "firstName": "Uriel", "lastName": "Collete", "age": 16 },
    { "id": 74, "firstName": "Claudie", "lastName": "Wathen", "age": 21 },
    { "id": 75, "firstName": "Althea", "lastName": "Anstiss", "age": 28 },
    { "id": 76, "firstName": "Betty", "lastName": "Naisbet", "age": 47 },
    { "id": 77, "firstName": "Philis", "lastName": "McCloch", "age": 74 },
    { "id": 78, "firstName": "Marcille", "lastName": "Lars", "age": 42 },
    { "id": 79, "firstName": "Pia", "lastName": "Martins", "age": 84 },
    { "id": 80, "firstName": "Fairlie", "lastName": "Crighton", "age": 49 },
    { "id": 81, "firstName": "Bekki", "lastName": "Hecks", "age": 58 },
    { "id": 82, "firstName": "Bamby", "lastName": "Claypool", "age": 48 },
    { "id": 83, "firstName": "Melvin", "lastName": "Kiera", "age": 55 },
    { "id": 84, "firstName": "Diandra", "lastName": "Berford", "age": 54 },
    { "id": 85, "firstName": "Adrien", "lastName": "Beurich", "age": 65 },
    { "id": 86, "firstName": "Lavinie", "lastName": "Hinrichs", "age": 84 },
    { "id": 87, "firstName": "Lianna", "lastName": "Lathwell", "age": 76 },
    { "id": 88, "firstName": "Dorris", "lastName": "Pittman", "age": 33 },
    { "id": 89, "firstName": "Effie", "lastName": "Sarge", "age": 53 },
    { "id": 90, "firstName": "Christean", "lastName": "Malpass", "age": 90 },
    { "id": 91, "firstName": "Herbie", "lastName": "Rymer", "age": 37 },
    { "id": 92, "firstName": "Karlen", "lastName": "Scarff", "age": 50 },
    { "id": 93, "firstName": "Auguste", "lastName": "Ruddock", "age": 85 },
    { "id": 94, "firstName": "Aguste", "lastName": "McQuilliam", "age": 53 },
    { "id": 95, "firstName": "Alvy", "lastName": "Pancoast", "age": 36 },
    { "id": 96, "firstName": "Remy", "lastName": "Posthill", "age": 19 },
    { "id": 97, "firstName": "Grace", "lastName": "Boyland", "age": 25 },
    { "id": 98, "firstName": "Alic", "lastName": "Sprake", "age": 54 },
    { "id": 99, "firstName": "Odella", "lastName": "Borley", "age": 61 },
    { "id": 100, "firstName": "Rudolfo", "lastName": "Gout", "age": 38 },
    { "id": 101, "firstName": "Alika", "lastName": "Callen", "age": 24 },
    { "id": 102, "firstName": "Else", "lastName": "Cressar", "age": 81 },
    { "id": 103, "firstName": "Khalil", "lastName": "Puttnam", "age": 90 },
    { "id": 104, "firstName": "Freedman", "lastName": "Dinsale", "age": 90 },
    { "id": 105, "firstName": "Cherice", "lastName": "Huison", "age": 72 },
    { "id": 106, "firstName": "Madella", "lastName": "Sertin", "age": 51 },
    { "id": 107, "firstName": "Friedrick", "lastName": "Lumbers", "age": 38 },
    { "id": 108, "firstName": "Carina", "lastName": "Badgers", "age": 43 },
    { "id": 109, "firstName": "Larine", "lastName": "Ivanishchev", "age": 82 },
    { "id": 110, "firstName": "Gerri", "lastName": "Vasin", "age": 82 },
    { "id": 111, "firstName": "Georgy", "lastName": "Jakaway", "age": 71 },
    { "id": 112, "firstName": "Adan", "lastName": "Chazelas", "age": 67 },
    { "id": 113, "firstName": "Rosella", "lastName": "Hearnes", "age": 36 },
    { "id": 114, "firstName": "Connor", "lastName": "Hurley", "age": 82 },
    { "id": 115, "firstName": "Jayne", "lastName": "Esmond", "age": 64 },
    { "id": 116, "firstName": "Derrick", "lastName": "Farnworth", "age": 57 },
    { "id": 117, "firstName": "Alphonso", "lastName": "Zecchii", "age": 76 },
    { "id": 118, "firstName": "Gino", "lastName": "Morsey", "age": 19 },
    { "id": 119, "firstName": "Nico", "lastName": "Kitman", "age": 30 },
    { "id": 120, "firstName": "Carla", "lastName": "Courtese", "age": 69 },
    { "id": 121, "firstName": "Elberta", "lastName": "Paramore", "age": 26 },
    { "id": 122, "firstName": "Duane", "lastName": "Turnell", "age": 81 },
    { "id": 123, "firstName": "Nikos", "lastName": "Fist", "age": 16 },
    { "id": 124, "firstName": "Laird", "lastName": "Ricks", "age": 48 },
    { "id": 125, "firstName": "Mella", "lastName": "Bover", "age": 23 },
    { "id": 126, "firstName": "Harley", "lastName": "Trodler", "age": 79 },
    { "id": 127, "firstName": "Max", "lastName": "Ornils", "age": 56 },
    { "id": 128, "firstName": "Norine", "lastName": "Spenclay", "age": 88 },
    { "id": 129, "firstName": "Norton", "lastName": "Stote", "age": 87 },
    { "id": 130, "firstName": "Vitia", "lastName": "Penvarden", "age": 48 },
    { "id": 131, "firstName": "Amata", "lastName": "Hammerberger", "age": 79 },
    { "id": 132, "firstName": "Jamal", "lastName": "Honig", "age": 21 },
    { "id": 133, "firstName": "Anatola", "lastName": "Leeman", "age": 63 },
    { "id": 134, "firstName": "Vlad", "lastName": "Alwin", "age": 50 },
    { "id": 135, "firstName": "Malanie", "lastName": "Tire", "age": 34 },
    { "id": 136, "firstName": "Sal", "lastName": "Jakel", "age": 25 },
    { "id": 137, "firstName": "Morly", "lastName": "Waleran", "age": 38 },
    { "id": 138, "firstName": "Kamila", "lastName": "Gartenfeld", "age": 86 },
    { "id": 139, "firstName": "Isabella", "lastName": "Hugo", "age": 85 },
    { "id": 140, "firstName": "Denise", "lastName": "Sisson", "age": 48 },
    { "id": 141, "firstName": "Otes", "lastName": "Candish", "age": 25 },
    { "id": 142, "firstName": "Avril", "lastName": "Bibey", "age": 88 },
    { "id": 143, "firstName": "Chad", "lastName": "Franses", "age": 34 },
    { "id": 144, "firstName": "Fernande", "lastName": "Livings", "age": 76 },
    { "id": 145, "firstName": "Noll", "lastName": "Valens-Smith", "age": 31 },
    { "id": 146, "firstName": "Benni", "lastName": "Fantin", "age": 44 },
    { "id": 147, "firstName": "Shalom", "lastName": "Kennerknecht", "age": 77 },
    { "id": 148, "firstName": "Jermain", "lastName": "Physick", "age": 79 },
    { "id": 149, "firstName": "Mersey", "lastName": "Elsy", "age": 62 },
    { "id": 150, "firstName": "Shelba", "lastName": "Lanegran", "age": 54 },
    { "id": 151, "firstName": "Rooney", "lastName": "Learoid", "age": 20 },
    { "id": 152, "firstName": "Lonny", "lastName": "Crufts", "age": 83 },
    { "id": 153, "firstName": "Cymbre", "lastName": "McAdam", "age": 32 },
    { "id": 154, "firstName": "Porty", "lastName": "Edelman", "age": 25 },
    { "id": 155, "firstName": "Jerald", "lastName": "Hartmann", "age": 18 },
    { "id": 156, "firstName": "Asia", "lastName": "Rosenfrucht", "age": 54 },
    { "id": 157, "firstName": "Giralda", "lastName": "Searston", "age": 21 },
    { "id": 158, "firstName": "Torin", "lastName": "Murison", "age": 16 },
    { "id": 159, "firstName": "Seward", "lastName": "Odney", "age": 70 },
    { "id": 160, "firstName": "Judd", "lastName": "Varfolomeev", "age": 15 },
    { "id": 161, "firstName": "Carlin", "lastName": "Abazi", "age": 75 },
    { "id": 162, "firstName": "Thorndike", "lastName": "Gillespey", "age": 39 },
    { "id": 163, "firstName": "Levon", "lastName": "Bugge", "age": 52 },
    { "id": 164, "firstName": "Marsiella", "lastName": "Ewebank", "age": 86 },
    { "id": 165, "firstName": "Alic", "lastName": "Knellen", "age": 76 },
    { "id": 166, "firstName": "Meryl", "lastName": "Heggs", "age": 73 },
    { "id": 167, "firstName": "Chuck", "lastName": "Yarr", "age": 44 },
    { "id": 168, "firstName": "Ervin", "lastName": "Seager", "age": 29 },
    { "id": 169, "firstName": "Yurik", "lastName": "Mougenel", "age": 32 },
    { "id": 170, "firstName": "Sara", "lastName": "Wadforth", "age": 51 },
    { "id": 171, "firstName": "Pammie", "lastName": "Mimmack", "age": 76 },
    { "id": 172, "firstName": "Gui", "lastName": "Buckle", "age": 46 },
    { "id": 173, "firstName": "Stanton", "lastName": "Kopfer", "age": 83 },
    { "id": 174, "firstName": "Lynn", "lastName": "Sommer", "age": 75 },
    {
      "id": 175,
      "firstName": "Bartolomeo",
      "lastName": "Brackpool",
      "age": 78
    },
    { "id": 176, "firstName": "Emogene", "lastName": "Frapwell", "age": 43 },
    { "id": 177, "firstName": "Katrina", "lastName": "Watkiss", "age": 22 },
    { "id": 178, "firstName": "Ab", "lastName": "Peron", "age": 40 },
    { "id": 179, "firstName": "Freddie", "lastName": "Elflain", "age": 34 },
    { "id": 180, "firstName": "Caye", "lastName": "Sammes", "age": 26 },
    { "id": 181, "firstName": "Krishnah", "lastName": "Nares", "age": 84 },
    { "id": 182, "firstName": "Courtnay", "lastName": "Maltby", "age": 15 },
    { "id": 183, "firstName": "Laure", "lastName": "Crayker", "age": 79 },
    { "id": 184, "firstName": "Sibella", "lastName": "Pennycord", "age": 72 },
    { "id": 185, "firstName": "Radcliffe", "lastName": "Bowhey", "age": 71 },
    { "id": 186, "firstName": "Marje", "lastName": "Foucard", "age": 37 },
    { "id": 187, "firstName": "Harriette", "lastName": "Hudel", "age": 41 },
    { "id": 188, "firstName": "Belinda", "lastName": "Boissier", "age": 37 },
    { "id": 189, "firstName": "Killie", "lastName": "Parlott", "age": 66 },
    { "id": 190, "firstName": "Darsie", "lastName": "Ivanyushin", "age": 40 },
    { "id": 191, "firstName": "Gearard", "lastName": "Casotti", "age": 35 },
    { "id": 192, "firstName": "Eward", "lastName": "Corfield", "age": 21 },
    { "id": 193, "firstName": "Tonie", "lastName": "Bradder", "age": 36 },
    { "id": 194, "firstName": "Issy", "lastName": "Roeby", "age": 65 },
    { "id": 195, "firstName": "Pearla", "lastName": "Ornelas", "age": 52 },
    { "id": 196, "firstName": "Saree", "lastName": "Burdess", "age": 42 },
    { "id": 197, "firstName": "Jennine", "lastName": "Counihan", "age": 64 },
    { "id": 198, "firstName": "Linc", "lastName": "Bloom", "age": 47 },
    { "id": 199, "firstName": "Briana", "lastName": "Bilbie", "age": 71 },
    { "id": 200, "firstName": "Homerus", "lastName": "Schreiner", "age": 40 },
    { "id": 201, "firstName": "Josie", "lastName": "Picot", "age": 48 },
    { "id": 202, "firstName": "Karissa", "lastName": "Norridge", "age": 79 },
    { "id": 203, "firstName": "Melisse", "lastName": "Gonsalvez", "age": 24 },
    { "id": 204, "firstName": "Neala", "lastName": "Millership", "age": 70 },
    {
      "id": 205,
      "firstName": "Carma",
      "lastName": "Jedrzejkiewicz",
      "age": 46
    },
    { "id": 206, "firstName": "Dollie", "lastName": "Chestle", "age": 66 },
    { "id": 207, "firstName": "Yasmeen", "lastName": "Ianelli", "age": 63 },
    { "id": 208, "firstName": "Carma", "lastName": "Hammill", "age": 82 },
    { "id": 209, "firstName": "Cord", "lastName": "Redborn", "age": 56 },
    { "id": 210, "firstName": "Kimmy", "lastName": "Pordal", "age": 83 },
    { "id": 211, "firstName": "Currey", "lastName": "Deener", "age": 35 },
    { "id": 212, "firstName": "Vinny", "lastName": "Chart", "age": 21 },
    { "id": 213, "firstName": "Rae", "lastName": "Sparhawk", "age": 51 },
    { "id": 214, "firstName": "Riobard", "lastName": "Cantor", "age": 90 },
    { "id": 215, "firstName": "Lalo", "lastName": "Heaford", "age": 90 },
    { "id": 216, "firstName": "Ivette", "lastName": "Conlaund", "age": 60 },
    { "id": 217, "firstName": "Albertina", "lastName": "Mordaunt", "age": 35 },
    { "id": 218, "firstName": "Alane", "lastName": "Hathwood", "age": 87 },
    { "id": 219, "firstName": "Wald", "lastName": "Grenville", "age": 19 },
    { "id": 220, "firstName": "Lindsey", "lastName": "Grimsdale", "age": 87 },
    { "id": 221, "firstName": "Dolores", "lastName": "Austin", "age": 30 },
    { "id": 222, "firstName": "Grantham", "lastName": "St Quenin", "age": 69 },
    { "id": 223, "firstName": "Linnet", "lastName": "Huxstep", "age": 78 },
    { "id": 224, "firstName": "Ernaline", "lastName": "Eynaud", "age": 59 },
    { "id": 225, "firstName": "Mic", "lastName": "Layus", "age": 41 },
    { "id": 226, "firstName": "Wilone", "lastName": "Sam", "age": 37 },
    { "id": 227, "firstName": "Gav", "lastName": "Gravy", "age": 15 },
    { "id": 228, "firstName": "Charmain", "lastName": "Tomsu", "age": 36 },
    { "id": 229, "firstName": "Peyton", "lastName": "Diggins", "age": 48 },
    { "id": 230, "firstName": "Dalia", "lastName": "Womersley", "age": 24 },
    { "id": 231, "firstName": "Nanni", "lastName": "Figgures", "age": 41 },
    { "id": 232, "firstName": "Philip", "lastName": "Nathan", "age": 64 },
    { "id": 233, "firstName": "Ardyce", "lastName": "Newcomb", "age": 62 },
    { "id": 234, "firstName": "Emmy", "lastName": "Volcker", "age": 39 },
    { "id": 235, "firstName": "Kiele", "lastName": "Izat", "age": 73 },
    { "id": 236, "firstName": "Quintilla", "lastName": "Benduhn", "age": 65 },
    { "id": 237, "firstName": "Diane", "lastName": "Leglise", "age": 60 },
    { "id": 238, "firstName": "Willi", "lastName": "Polley", "age": 59 },
    { "id": 239, "firstName": "Rickey", "lastName": "Dine-Hart", "age": 46 },
    { "id": 240, "firstName": "Emmanuel", "lastName": "Goldfinch", "age": 72 },
    { "id": 241, "firstName": "Fairfax", "lastName": "Tapsfield", "age": 42 },
    { "id": 242, "firstName": "Benedetto", "lastName": "Giddins", "age": 83 },
    { "id": 243, "firstName": "Antoni", "lastName": "Kilsby", "age": 70 },
    { "id": 244, "firstName": "Onfre", "lastName": "Carnow", "age": 43 },
    { "id": 245, "firstName": "Danny", "lastName": "Gini", "age": 82 },
    { "id": 246, "firstName": "Lula", "lastName": "De Brett", "age": 89 },
    { "id": 247, "firstName": "Emeline", "lastName": "Clews", "age": 57 },
    { "id": 248, "firstName": "Blanch", "lastName": "Stefi", "age": 28 },
    { "id": 249, "firstName": "Nicolina", "lastName": "Ferry", "age": 71 },
    { "id": 250, "firstName": "Sarina", "lastName": "Stevens", "age": 89 },
    { "id": 251, "firstName": "Putnam", "lastName": "Boosey", "age": 28 },
    { "id": 252, "firstName": "Zorine", "lastName": "Coie", "age": 55 },
    { "id": 253, "firstName": "Creight", "lastName": "Switzer", "age": 65 },
    { "id": 254, "firstName": "Glen", "lastName": "Raftery", "age": 70 },
    { "id": 255, "firstName": "Merrill", "lastName": "Duffin", "age": 61 },
    { "id": 256, "firstName": "Sella", "lastName": "Duckering", "age": 77 },
    { "id": 257, "firstName": "Karoly", "lastName": "Cleminshaw", "age": 77 },
    { "id": 258, "firstName": "Cyrus", "lastName": "Lufkin", "age": 36 },
    { "id": 259, "firstName": "Anette", "lastName": "Tann", "age": 89 },
    { "id": 260, "firstName": "Cora", "lastName": "Marielle", "age": 51 },
    { "id": 261, "firstName": "Mead", "lastName": "Annwyl", "age": 27 },
    { "id": 262, "firstName": "Nataniel", "lastName": "Jaksic", "age": 29 },
    { "id": 263, "firstName": "Yolanda", "lastName": "Dagger", "age": 19 },
    { "id": 264, "firstName": "Friederike", "lastName": "Barlie", "age": 47 },
    { "id": 265, "firstName": "Daloris", "lastName": "Streeting", "age": 29 },
    { "id": 266, "firstName": "Sherlocke", "lastName": "Imason", "age": 34 },
    { "id": 267, "firstName": "Britni", "lastName": "Kohnen", "age": 38 },
    { "id": 268, "firstName": "Amble", "lastName": "Birchenhead", "age": 17 },
    { "id": 269, "firstName": "Trude", "lastName": "Seville", "age": 89 },
    { "id": 270, "firstName": "Cyrillus", "lastName": "Ughelli", "age": 67 },
    { "id": 271, "firstName": "Mayer", "lastName": "Vawton", "age": 24 },
    { "id": 272, "firstName": "Josias", "lastName": "Casaccio", "age": 63 },
    { "id": 273, "firstName": "Samuele", "lastName": "Bernet", "age": 29 },
    { "id": 274, "firstName": "Liza", "lastName": "Kield", "age": 58 },
    { "id": 275, "firstName": "Mindy", "lastName": "Alty", "age": 40 },
    { "id": 276, "firstName": "Derron", "lastName": "Sworne", "age": 34 },
    { "id": 277, "firstName": "Britt", "lastName": "Bulmer", "age": 55 },
    { "id": 278, "firstName": "Wynny", "lastName": "Lawee", "age": 50 },
    { "id": 279, "firstName": "Eliot", "lastName": "Salaman", "age": 46 },
    { "id": 280, "firstName": "Wolfgang", "lastName": "Ahlf", "age": 32 },
    { "id": 281, "firstName": "Nadiya", "lastName": "Pheazey", "age": 90 },
    { "id": 282, "firstName": "Stella", "lastName": "Wedgwood", "age": 77 },
    { "id": 283, "firstName": "Cleopatra", "lastName": "Seleway", "age": 16 },
    { "id": 284, "firstName": "Ina", "lastName": "Skatcher", "age": 47 },
    { "id": 285, "firstName": "Fania", "lastName": "Leyre", "age": 48 },
    { "id": 286, "firstName": "Simone", "lastName": "Wiffler", "age": 42 },
    { "id": 287, "firstName": "Caroline", "lastName": "Duffil", "age": 46 },
    { "id": 288, "firstName": "Dido", "lastName": "Zanettini", "age": 39 },
    { "id": 289, "firstName": "Brana", "lastName": "Deere", "age": 26 },
    { "id": 290, "firstName": "Hansiain", "lastName": "Robbie", "age": 77 },
    { "id": 291, "firstName": "Olivette", "lastName": "Jancar", "age": 90 },
    { "id": 292, "firstName": "Tish", "lastName": "Rushforth", "age": 87 },
    { "id": 293, "firstName": "Gasparo", "lastName": "Jozwiak", "age": 75 },
    { "id": 294, "firstName": "Jonathan", "lastName": "Mompesson", "age": 27 },
    { "id": 295, "firstName": "Jillayne", "lastName": "Ber", "age": 55 },
    { "id": 296, "firstName": "Mariam", "lastName": "Strelitz", "age": 54 },
    { "id": 297, "firstName": "Miller", "lastName": "Ciardo", "age": 48 },
    { "id": 298, "firstName": "Clyve", "lastName": "Insull", "age": 35 },
    { "id": 299, "firstName": "Kitty", "lastName": "Seiller", "age": 30 },
    { "id": 300, "firstName": "Nigel", "lastName": "Ivatt", "age": 29 },
    { "id": 301, "firstName": "Janette", "lastName": "Feeley", "age": 17 },
    { "id": 302, "firstName": "Allina", "lastName": "McKinty", "age": 35 },
    { "id": 303, "firstName": "Francene", "lastName": "Matusov", "age": 69 },
    { "id": 304, "firstName": "Artemus", "lastName": "Carmo", "age": 15 },
    { "id": 305, "firstName": "Jeremie", "lastName": "Cockrill", "age": 88 },
    { "id": 306, "firstName": "Taddeo", "lastName": "Barfield", "age": 41 },
    { "id": 307, "firstName": "Joaquin", "lastName": "Iacomettii", "age": 89 },
    { "id": 308, "firstName": "Flin", "lastName": "Allott", "age": 70 },
    { "id": 309, "firstName": "Meridith", "lastName": "Mertgen", "age": 77 },
    { "id": 310, "firstName": "Lorin", "lastName": "Purkess", "age": 48 },
    { "id": 311, "firstName": "Eli", "lastName": "Preshaw", "age": 71 },
    { "id": 312, "firstName": "Arvie", "lastName": "Drawmer", "age": 59 },
    { "id": 313, "firstName": "Sue", "lastName": "Fearns", "age": 31 },
    { "id": 314, "firstName": "Lori", "lastName": "Fumagallo", "age": 32 },
    { "id": 315, "firstName": "Jose", "lastName": "Skayman", "age": 21 },
    { "id": 316, "firstName": "Graig", "lastName": "Downing", "age": 77 },
    { "id": 317, "firstName": "Dinah", "lastName": "Leadbeatter", "age": 28 },
    { "id": 318, "firstName": "Alano", "lastName": "Ambrosch", "age": 63 },
    { "id": 319, "firstName": "Daveen", "lastName": "Commins", "age": 70 },
    { "id": 320, "firstName": "Eloise", "lastName": "Duffrie", "age": 45 },
    { "id": 321, "firstName": "Valina", "lastName": "Maginn", "age": 31 },
    { "id": 322, "firstName": "Katerina", "lastName": "Tyres", "age": 20 },
    { "id": 323, "firstName": "Carree", "lastName": "Gloyens", "age": 22 },
    { "id": 324, "firstName": "Bayard", "lastName": "Burchill", "age": 52 },
    { "id": 325, "firstName": "Augy", "lastName": "Heitz", "age": 87 },
    { "id": 326, "firstName": "Marlane", "lastName": "Kelley", "age": 37 },
    { "id": 327, "firstName": "Thacher", "lastName": "Mainson", "age": 74 },
    { "id": 328, "firstName": "Fayth", "lastName": "Vowells", "age": 64 },
    { "id": 329, "firstName": "Bibby", "lastName": "Crowthe", "age": 82 },
    { "id": 330, "firstName": "Ardyce", "lastName": "Goddman", "age": 72 },
    { "id": 331, "firstName": "Alina", "lastName": "Karpenko", "age": 24 },
    { "id": 332, "firstName": "Meredith", "lastName": "Shiers", "age": 47 },
    { "id": 333, "firstName": "Jan", "lastName": "Brothwell", "age": 51 },
    { "id": 334, "firstName": "Moritz", "lastName": "Tembey", "age": 31 },
    { "id": 335, "firstName": "Pamella", "lastName": "Isakson", "age": 23 },
    { "id": 336, "firstName": "Rafe", "lastName": "Ashfull", "age": 89 },
    { "id": 337, "firstName": "North", "lastName": "L' Estrange", "age": 68 },
    { "id": 338, "firstName": "Idette", "lastName": "Stradling", "age": 64 },
    { "id": 339, "firstName": "Kariotta", "lastName": "Gammie", "age": 68 },
    { "id": 340, "firstName": "Bald", "lastName": "Oxshott", "age": 16 },
    { "id": 341, "firstName": "Roscoe", "lastName": "Eddins", "age": 56 },
    { "id": 342, "firstName": "Meris", "lastName": "Duncklee", "age": 32 },
    { "id": 343, "firstName": "Siana", "lastName": "Cuniffe", "age": 53 },
    { "id": 344, "firstName": "Lurleen", "lastName": "Bearcock", "age": 69 },
    { "id": 345, "firstName": "Marlo", "lastName": "Shackleford", "age": 56 },
    { "id": 346, "firstName": "Chrotoem", "lastName": "Chazette", "age": 17 },
    { "id": 347, "firstName": "Theobald", "lastName": "Seville", "age": 68 },
    { "id": 348, "firstName": "Kinnie", "lastName": "Goody", "age": 85 },
    { "id": 349, "firstName": "Lizzie", "lastName": "Barbie", "age": 77 },
    { "id": 350, "firstName": "Christian", "lastName": "Bye", "age": 55 },
    { "id": 351, "firstName": "Garry", "lastName": "Balsom", "age": 15 },
    { "id": 352, "firstName": "Bogart", "lastName": "Mariot", "age": 46 },
    { "id": 353, "firstName": "Annemarie", "lastName": "Beglin", "age": 61 },
    { "id": 354, "firstName": "Elissa", "lastName": "Roughan", "age": 39 },
    { "id": 355, "firstName": "Sky", "lastName": "Marsland", "age": 58 },
    { "id": 356, "firstName": "Ange", "lastName": "McGavin", "age": 31 },
    { "id": 357, "firstName": "Hunt", "lastName": "Ricketts", "age": 86 },
    { "id": 358, "firstName": "Cori", "lastName": "Rough", "age": 44 },
    { "id": 359, "firstName": "Felice", "lastName": "McGrah", "age": 51 },
    { "id": 360, "firstName": "Corny", "lastName": "Ebbage", "age": 47 },
    { "id": 361, "firstName": "Aili", "lastName": "Brewitt", "age": 90 },
    { "id": 362, "firstName": "Bobinette", "lastName": "Guilaem", "age": 24 },
    { "id": 363, "firstName": "Blisse", "lastName": "Hincks", "age": 33 },
    { "id": 364, "firstName": "Morna", "lastName": "Rottcher", "age": 35 },
    { "id": 365, "firstName": "Shawna", "lastName": "Claessens", "age": 64 },
    { "id": 366, "firstName": "Sallyann", "lastName": "Hutchason", "age": 17 },
    { "id": 367, "firstName": "Jessamine", "lastName": "Stutte", "age": 56 },
    { "id": 368, "firstName": "Elton", "lastName": "Dubose", "age": 35 },
    { "id": 369, "firstName": "Karalynn", "lastName": "Pratley", "age": 51 },
    { "id": 370, "firstName": "Rubin", "lastName": "Ashman", "age": 22 },
    { "id": 371, "firstName": "Shanan", "lastName": "Jozsa", "age": 32 },
    { "id": 372, "firstName": "Lauralee", "lastName": "Pikesley", "age": 62 },
    { "id": 373, "firstName": "Rufus", "lastName": "Wallbrook", "age": 15 },
    { "id": 374, "firstName": "Harman", "lastName": "Hawtrey", "age": 69 },
    { "id": 375, "firstName": "Emalia", "lastName": "Juschka", "age": 15 },
    { "id": 376, "firstName": "Missie", "lastName": "Ruoff", "age": 42 },
    { "id": 377, "firstName": "Buddie", "lastName": "Marielle", "age": 46 },
    { "id": 378, "firstName": "Maison", "lastName": "MacNish", "age": 74 },
    { "id": 379, "firstName": "Stormi", "lastName": "Boler", "age": 54 },
    { "id": 380, "firstName": "Flinn", "lastName": "Featherstone", "age": 78 },
    { "id": 381, "firstName": "Irwinn", "lastName": "Brocklehurst", "age": 18 },
    { "id": 382, "firstName": "Konstance", "lastName": "Spurman", "age": 60 },
    { "id": 383, "firstName": "Becca", "lastName": "Razoux", "age": 38 },
    { "id": 384, "firstName": "Iain", "lastName": "Troubridge", "age": 88 },
    { "id": 385, "firstName": "Cami", "lastName": "Phelip", "age": 52 },
    { "id": 386, "firstName": "Aldin", "lastName": "Solesbury", "age": 49 },
    { "id": 387, "firstName": "Hanny", "lastName": "Micklewicz", "age": 16 },
    { "id": 388, "firstName": "Clyve", "lastName": "Arends", "age": 15 },
    { "id": 389, "firstName": "Bernadine", "lastName": "Fradgley", "age": 31 },
    { "id": 390, "firstName": "Muire", "lastName": "Vardie", "age": 90 },
    { "id": 391, "firstName": "Isabel", "lastName": "Harnott", "age": 71 },
    { "id": 392, "firstName": "Gus", "lastName": "Ca", "age": 65 },
    { "id": 393, "firstName": "Corinna", "lastName": "Poone", "age": 21 },
    { "id": 394, "firstName": "Donal", "lastName": "Spohrmann", "age": 50 },
    { "id": 395, "firstName": "Renata", "lastName": "Sieb", "age": 78 },
    { "id": 396, "firstName": "Mavis", "lastName": "Bysouth", "age": 46 },
    { "id": 397, "firstName": "Parker", "lastName": "Caulfield", "age": 65 },
    { "id": 398, "firstName": "Franky", "lastName": "O'Donohue", "age": 40 },
    { "id": 399, "firstName": "Gillie", "lastName": "Sharpin", "age": 24 },
    { "id": 400, "firstName": "Sarajane", "lastName": "Gayler", "age": 23 },
    { "id": 401, "firstName": "Cesar", "lastName": "Megarry", "age": 78 },
    { "id": 402, "firstName": "Sansone", "lastName": "Zumbusch", "age": 89 },
    { "id": 403, "firstName": "Stevie", "lastName": "De Hooch", "age": 80 },
    { "id": 404, "firstName": "Neille", "lastName": "Riha", "age": 19 },
    { "id": 405, "firstName": "Ashlen", "lastName": "Edgeon", "age": 65 },
    { "id": 406, "firstName": "Griswold", "lastName": "Boggas", "age": 26 },
    { "id": 407, "firstName": "Umeko", "lastName": "Braemer", "age": 39 },
    { "id": 408, "firstName": "Odelia", "lastName": "von Nassau", "age": 75 },
    { "id": 409, "firstName": "Derick", "lastName": "Gosnell", "age": 19 },
    { "id": 410, "firstName": "Junina", "lastName": "Capnor", "age": 45 },
    { "id": 411, "firstName": "Barnabas", "lastName": "Nutt", "age": 64 },
    { "id": 412, "firstName": "Myrle", "lastName": "Bradock", "age": 17 },
    { "id": 413, "firstName": "Kyle", "lastName": "Egginton", "age": 59 },
    {
      "id": 414,
      "firstName": "Cameron",
      "lastName": "O' Mulderrig",
      "age": 70
    },
    { "id": 415, "firstName": "Astrid", "lastName": "Laight", "age": 44 },
    { "id": 416, "firstName": "Anna-maria", "lastName": "Fifield", "age": 16 },
    { "id": 417, "firstName": "Jehu", "lastName": "Vidineev", "age": 19 },
    { "id": 418, "firstName": "Miof mela", "lastName": "Knowlson", "age": 40 },
    { "id": 419, "firstName": "Eberhard", "lastName": "Plaster", "age": 31 },
    { "id": 420, "firstName": "Arleen", "lastName": "Killcross", "age": 39 },
    { "id": 421, "firstName": "Patty", "lastName": "Domm", "age": 33 },
    { "id": 422, "firstName": "Jordan", "lastName": "Hall", "age": 90 },
    { "id": 423, "firstName": "Bell", "lastName": "Lamasna", "age": 88 },
    { "id": 424, "firstName": "Juan", "lastName": "Bottomer", "age": 73 },
    { "id": 425, "firstName": "Michell", "lastName": "Mompesson", "age": 59 },
    { "id": 426, "firstName": "Bastian", "lastName": "Ewing", "age": 65 },
    { "id": 427, "firstName": "Arnold", "lastName": "Shilleto", "age": 70 },
    { "id": 428, "firstName": "Barnabe", "lastName": "Bortoletti", "age": 19 },
    { "id": 429, "firstName": "Concordia", "lastName": "Wildsmith", "age": 49 },
    { "id": 430, "firstName": "Tasha", "lastName": "Klimaszewski", "age": 46 },
    { "id": 431, "firstName": "Mureil", "lastName": "O'Coskerry", "age": 43 },
    { "id": 432, "firstName": "Wally", "lastName": "Winham", "age": 20 },
    { "id": 433, "firstName": "Cassie", "lastName": "Privost", "age": 50 },
    { "id": 434, "firstName": "Cletus", "lastName": "Jain", "age": 41 },
    { "id": 435, "firstName": "Winslow", "lastName": "Romeo", "age": 67 },
    { "id": 436, "firstName": "Dorey", "lastName": "O'Kennedy", "age": 70 },
    { "id": 437, "firstName": "Marieann", "lastName": "Swindin", "age": 55 },
    { "id": 438, "firstName": "Michaella", "lastName": "Cianelli", "age": 69 },
    { "id": 439, "firstName": "Hallsy", "lastName": "Rasher", "age": 55 },
    { "id": 440, "firstName": "Nora", "lastName": "Drinkel", "age": 44 },
    { "id": 441, "firstName": "Janice", "lastName": "Teese", "age": 87 },
    { "id": 442, "firstName": "Mignonne", "lastName": "Virgin", "age": 67 },
    { "id": 443, "firstName": "Genia", "lastName": "Burriss", "age": 65 },
    { "id": 444, "firstName": "Briano", "lastName": "Cheake", "age": 83 },
    { "id": 445, "firstName": "Bertine", "lastName": "Kenworthey", "age": 18 },
    { "id": 446, "firstName": "Minna", "lastName": "Laugharne", "age": 70 },
    { "id": 447, "firstName": "Karlen", "lastName": "Sitford", "age": 26 },
    { "id": 448, "firstName": "Sauncho", "lastName": "Sheasby", "age": 41 },
    { "id": 449, "firstName": "Vladimir", "lastName": "Proven", "age": 74 },
    { "id": 450, "firstName": "Ambrosio", "lastName": "Mounfield", "age": 66 },
    { "id": 451, "firstName": "Lisa", "lastName": "Restorick", "age": 79 },
    { "id": 452, "firstName": "Ax", "lastName": "Hunnisett", "age": 76 },
    { "id": 453, "firstName": "Hastie", "lastName": "O'Brian", "age": 66 },
    { "id": 454, "firstName": "Lewiss", "lastName": "Glendza", "age": 57 },
    { "id": 455, "firstName": "Ryon", "lastName": "Klaves", "age": 82 },
    { "id": 456, "firstName": "Maura", "lastName": "Sharples", "age": 18 },
    { "id": 457, "firstName": "Suki", "lastName": "Loudian", "age": 44 },
    { "id": 458, "firstName": "Rodolph", "lastName": "Kitcherside", "age": 27 },
    { "id": 459, "firstName": "Quintana", "lastName": "Kobiela", "age": 17 },
    { "id": 460, "firstName": "Elberta", "lastName": "Risbrough", "age": 20 },
    { "id": 461, "firstName": "Farly", "lastName": "Fessby", "age": 23 },
    { "id": 462, "firstName": "Ninnetta", "lastName": "Lynd", "age": 16 },
    { "id": 463, "firstName": "Julita", "lastName": "Reveley", "age": 23 },
    { "id": 464, "firstName": "Teriann", "lastName": "Crowcroft", "age": 70 },
    { "id": 465, "firstName": "Sid", "lastName": "Hannigan", "age": 64 },
    { "id": 466, "firstName": "Allix", "lastName": "Gerrish", "age": 83 },
    { "id": 467, "firstName": "Seka", "lastName": "Gowthrop", "age": 79 },
    { "id": 468, "firstName": "Gonzalo", "lastName": "Haresign", "age": 45 },
    { "id": 469, "firstName": "Rosamond", "lastName": "Gorgl", "age": 88 },
    { "id": 470, "firstName": "Tamas", "lastName": "Symonds", "age": 60 },
    { "id": 471, "firstName": "Naomi", "lastName": "Heads", "age": 72 },
    { "id": 472, "firstName": "Constantia", "lastName": "Ricardo", "age": 39 },
    { "id": 473, "firstName": "Bobine", "lastName": "Watting", "age": 83 },
    { "id": 474, "firstName": "Josie", "lastName": "Meese", "age": 30 },
    { "id": 475, "firstName": "Siana", "lastName": "Haibel", "age": 83 },
    { "id": 476, "firstName": "Frederigo", "lastName": "Anthiftle", "age": 57 },
    { "id": 477, "firstName": "Ricky", "lastName": "Giacomo", "age": 45 },
    { "id": 478, "firstName": "Garvey", "lastName": "O'Halligan", "age": 30 },
    { "id": 479, "firstName": "Roderigo", "lastName": "Skaif", "age": 38 },
    { "id": 480, "firstName": "Odilia", "lastName": "Twidale", "age": 52 },
    { "id": 481, "firstName": "Isabel", "lastName": "Baise", "age": 49 },
    { "id": 482, "firstName": "Cathi", "lastName": "Emes", "age": 40 },
    { "id": 483, "firstName": "Tobey", "lastName": "Madle", "age": 22 },
    { "id": 484, "firstName": "Bella", "lastName": "Schoolcroft", "age": 16 },
    { "id": 485, "firstName": "Janith", "lastName": "Ivanov", "age": 69 },
    { "id": 486, "firstName": "Garrott", "lastName": "Mellem", "age": 49 },
    { "id": 487, "firstName": "Belvia", "lastName": "Stickles", "age": 37 },
    { "id": 488, "firstName": "Eleni", "lastName": "Blaksley", "age": 65 },
    { "id": 489, "firstName": "Andria", "lastName": "Blankenship", "age": 47 },
    { "id": 490, "firstName": "Alard", "lastName": "MacGaughy", "age": 79 },
    { "id": 491, "firstName": "Shari", "lastName": "Gofforth", "age": 16 },
    { "id": 492, "firstName": "Diane", "lastName": "Cork", "age": 33 },
    { "id": 493, "firstName": "Winny", "lastName": "Hynde", "age": 82 },
    { "id": 494, "firstName": "Teodora", "lastName": "Splaven", "age": 55 },
    { "id": 495, "firstName": "Shela", "lastName": "Hucknall", "age": 18 },
    { "id": 496, "firstName": "Norene", "lastName": "Gregor", "age": 37 },
    { "id": 497, "firstName": "Sophi", "lastName": "Fiorentino", "age": 30 },
    { "id": 498, "firstName": "Harald", "lastName": "Brodeur", "age": 47 },
    { "id": 499, "firstName": "Rina", "lastName": "Domengue", "age": 66 },
    { "id": 500, "firstName": "Norbert", "lastName": "Bridge", "age": 55 },
    { "id": 501, "firstName": "Victoir", "lastName": "Hucknall", "age": 89 },
    { "id": 502, "firstName": "Griz", "lastName": "Cornbill", "age": 78 },
    { "id": 503, "firstName": "Chantalle", "lastName": "Lillicrap", "age": 71 },
    { "id": 504, "firstName": "Dolorita", "lastName": "Joesbury", "age": 59 },
    { "id": 505, "firstName": "Frasquito", "lastName": "Addess", "age": 20 },
    { "id": 506, "firstName": "Wiatt", "lastName": "Stollard", "age": 66 },
    { "id": 507, "firstName": "Carola", "lastName": "Fears", "age": 55 },
    { "id": 508, "firstName": "Geoff", "lastName": "Cecil", "age": 77 },
    { "id": 509, "firstName": "Abdel", "lastName": "Metts", "age": 62 },
    { "id": 510, "firstName": "Carita", "lastName": "Cockson", "age": 55 },
    { "id": 511, "firstName": "Tedra", "lastName": "Danielczyk", "age": 35 },
    { "id": 512, "firstName": "Redford", "lastName": "Quarton", "age": 37 },
    { "id": 513, "firstName": "Raye", "lastName": "Redford", "age": 77 },
    { "id": 514, "firstName": "Sula", "lastName": "Brookfield", "age": 53 },
    { "id": 515, "firstName": "Salomon", "lastName": "Causer", "age": 24 },
    { "id": 516, "firstName": "Brenda", "lastName": "Bushrod", "age": 61 },
    { "id": 517, "firstName": "Sanson", "lastName": "Kitchener", "age": 56 },
    { "id": 518, "firstName": "Jobye", "lastName": "Merington", "age": 78 },
    { "id": 519, "firstName": "Carri", "lastName": "Lysaght", "age": 29 },
    { "id": 520, "firstName": "Idell", "lastName": "Gopsill", "age": 63 },
    { "id": 521, "firstName": "Rebekah", "lastName": "Sunshine", "age": 33 },
    { "id": 522, "firstName": "Roman", "lastName": "Coniff", "age": 49 },
    { "id": 523, "firstName": "Olva", "lastName": "Leebeter", "age": 26 },
    { "id": 524, "firstName": "Lev", "lastName": "Lawrie", "age": 20 },
    { "id": 525, "firstName": "Ingra", "lastName": "Dowdall", "age": 64 },
    { "id": 526, "firstName": "Genna", "lastName": "Shead", "age": 65 },
    { "id": 527, "firstName": "Morris", "lastName": "Dumbrall", "age": 15 },
    { "id": 528, "firstName": "Owen", "lastName": "Jeffcock", "age": 87 },
    { "id": 529, "firstName": "Clo", "lastName": "Gabe", "age": 89 },
    { "id": 530, "firstName": "Eugenie", "lastName": "Sawood", "age": 54 },
    { "id": 531, "firstName": "Udale", "lastName": "Cranham", "age": 48 },
    { "id": 532, "firstName": "Isidro", "lastName": "Reinger", "age": 43 },
    { "id": 533, "firstName": "Chrystel", "lastName": "O'Heneghan", "age": 26 },
    { "id": 534, "firstName": "Elvis", "lastName": "Casford", "age": 44 },
    { "id": 535, "firstName": "Vitia", "lastName": "Bickell", "age": 28 },
    { "id": 536, "firstName": "Robinson", "lastName": "Harkins", "age": 66 },
    { "id": 537, "firstName": "Monti", "lastName": "Eckels", "age": 33 },
    { "id": 538, "firstName": "Rodolfo", "lastName": "Deane", "age": 65 },
    { "id": 539, "firstName": "Hallsy", "lastName": "Hovenden", "age": 24 },
    { "id": 540, "firstName": "Roxie", "lastName": "Saunderson", "age": 30 },
    { "id": 541, "firstName": "Ferdie", "lastName": "Yesichev", "age": 43 },
    { "id": 542, "firstName": "Melisenda", "lastName": "McCloch", "age": 84 },
    { "id": 543, "firstName": "Malinda", "lastName": "Finkle", "age": 40 },
    { "id": 544, "firstName": "Scarlett", "lastName": "Baleine", "age": 73 },
    { "id": 545, "firstName": "Barney", "lastName": "O'Driscoll", "age": 35 },
    { "id": 546, "firstName": "Bettye", "lastName": "Eagleton", "age": 70 },
    { "id": 547, "firstName": "Etti", "lastName": "Gilks", "age": 23 },
    { "id": 548, "firstName": "Dulcea", "lastName": "Joicey", "age": 90 },
    { "id": 549, "firstName": "Lidia", "lastName": "Cracie", "age": 46 },
    { "id": 550, "firstName": "Maison", "lastName": "Darbishire", "age": 32 },
    { "id": 551, "firstName": "Gael", "lastName": "Shields", "age": 42 },
    { "id": 552, "firstName": "Sunny", "lastName": "Twelvetree", "age": 32 },
    { "id": 553, "firstName": "Shelli", "lastName": "Westcot", "age": 55 },
    { "id": 554, "firstName": "Glenna", "lastName": "Marrows", "age": 89 },
    { "id": 555, "firstName": "Michell", "lastName": "Dimitriou", "age": 84 },
    { "id": 556, "firstName": "Kahlil", "lastName": "Borland", "age": 69 },
    { "id": 557, "firstName": "Donal", "lastName": "Slatten", "age": 45 },
    { "id": 558, "firstName": "Helsa", "lastName": "Sussems", "age": 47 },
    { "id": 559, "firstName": "Paolina", "lastName": "Newcombe", "age": 52 },
    { "id": 560, "firstName": "Ella", "lastName": "Valde", "age": 88 },
    { "id": 561, "firstName": "Cathleen", "lastName": "Guiduzzi", "age": 40 },
    { "id": 562, "firstName": "Cacilia", "lastName": "Hulburt", "age": 19 },
    { "id": 563, "firstName": "Jenda", "lastName": "O'Lenane", "age": 66 },
    { "id": 564, "firstName": "Electra", "lastName": "Reston", "age": 59 },
    { "id": 565, "firstName": "Modesty", "lastName": "Stockell", "age": 71 },
    { "id": 566, "firstName": "Cindie", "lastName": "Eatttok", "age": 61 },
    { "id": 567, "firstName": "Renell", "lastName": "Ellingworth", "age": 26 },
    { "id": 568, "firstName": "Lanae", "lastName": "Muirden", "age": 33 },
    { "id": 569, "firstName": "Melodee", "lastName": "Malec", "age": 16 },
    { "id": 570, "firstName": "Gerrie", "lastName": "Saylor", "age": 78 },
    { "id": 571, "firstName": "Ardisj", "lastName": "Ivory", "age": 68 },
    { "id": 572, "firstName": "Lily", "lastName": "Levay", "age": 20 },
    { "id": 573, "firstName": "Thibaut", "lastName": "Pourvoieur", "age": 35 },
    { "id": 574, "firstName": "Anni", "lastName": "Gary", "age": 64 },
    { "id": 575, "firstName": "Valeda", "lastName": "O'Sheeryne", "age": 17 },
    {
      "id": 576,
      "firstName": "Falkner",
      "lastName": "Van De Cappelle",
      "age": 34
    },
    { "id": 577, "firstName": "Fletch", "lastName": "Padgham", "age": 28 },
    { "id": 578, "firstName": "Jaine", "lastName": "Northwood", "age": 37 },
    { "id": 579, "firstName": "Pattin", "lastName": "Kenrat", "age": 72 },
    { "id": 580, "firstName": "Jordanna", "lastName": "Evennett", "age": 18 },
    { "id": 581, "firstName": "Asa", "lastName": "Meys", "age": 66 },
    { "id": 582, "firstName": "Giusto", "lastName": "Millward", "age": 53 },
    { "id": 583, "firstName": "Zackariah", "lastName": "Huygen", "age": 35 },
    { "id": 584, "firstName": "Cob", "lastName": "Clingoe", "age": 55 },
    { "id": 585, "firstName": "Cherilynn", "lastName": "Roglieri", "age": 80 },
    { "id": 586, "firstName": "Merci", "lastName": "Mingardo", "age": 16 },
    { "id": 587, "firstName": "Heath", "lastName": "Kleinerman", "age": 29 },
    { "id": 588, "firstName": "Bettina", "lastName": "Rupel", "age": 62 },
    { "id": 589, "firstName": "Jacynth", "lastName": "Pryor", "age": 61 },
    { "id": 590, "firstName": "Maud", "lastName": "Panton", "age": 49 },
    { "id": 591, "firstName": "Mart", "lastName": "Iacobetto", "age": 53 },
    { "id": 592, "firstName": "Tresa", "lastName": "Arkwright", "age": 78 },
    { "id": 593, "firstName": "Umeko", "lastName": "McAllen", "age": 50 },
    { "id": 594, "firstName": "Gianna", "lastName": "Ventris", "age": 33 },
    { "id": 595, "firstName": "Leontyne", "lastName": "Halle", "age": 79 },
    { "id": 596, "firstName": "Juanita", "lastName": "Cayley", "age": 43 },
    { "id": 597, "firstName": "Elora", "lastName": "Debow", "age": 60 },
    { "id": 598, "firstName": "Arabela", "lastName": "Smitheman", "age": 85 },
    { "id": 599, "firstName": "Liliane", "lastName": "Munden", "age": 58 },
    { "id": 600, "firstName": "Desmond", "lastName": "Marham", "age": 16 },
    { "id": 601, "firstName": "Barnabe", "lastName": "Revey", "age": 86 },
    { "id": 602, "firstName": "Hobart", "lastName": "Dering", "age": 44 },
    { "id": 603, "firstName": "Bea", "lastName": "Bordes", "age": 33 },
    { "id": 604, "firstName": "Harlen", "lastName": "Iredell", "age": 67 },
    { "id": 605, "firstName": "Abelard", "lastName": "Hiley", "age": 48 },
    { "id": 606, "firstName": "Jimmie", "lastName": "Hew", "age": 27 },
    { "id": 607, "firstName": "Danya", "lastName": "Letterick", "age": 77 },
    { "id": 608, "firstName": "Clive", "lastName": "Ritchman", "age": 19 },
    { "id": 609, "firstName": "Agnese", "lastName": "Lothean", "age": 62 },
    { "id": 610, "firstName": "Catherin", "lastName": "Cotilard", "age": 82 },
    { "id": 611, "firstName": "Tobe", "lastName": "Strothers", "age": 87 },
    { "id": 612, "firstName": "Cinnamon", "lastName": "McIlveen", "age": 21 },
    { "id": 613, "firstName": "Kaspar", "lastName": "Durek", "age": 37 },
    { "id": 614, "firstName": "Tymon", "lastName": "Semmens", "age": 74 },
    { "id": 615, "firstName": "Giffer", "lastName": "Gallimore", "age": 86 },
    { "id": 616, "firstName": "Mitch", "lastName": "Milbourne", "age": 62 },
    { "id": 617, "firstName": "Town", "lastName": "Oty", "age": 43 },
    { "id": 618, "firstName": "Rayner", "lastName": "Stuart", "age": 27 },
    { "id": 619, "firstName": "Mayer", "lastName": "Soffe", "age": 40 },
    { "id": 620, "firstName": "Marne", "lastName": "Vigars", "age": 32 },
    { "id": 621, "firstName": "Jeffie", "lastName": "Chattaway", "age": 23 },
    { "id": 622, "firstName": "Valentin", "lastName": "Romney", "age": 78 },
    { "id": 623, "firstName": "Alley", "lastName": "Cordova", "age": 89 },
    { "id": 624, "firstName": "Tasia", "lastName": "Hamner", "age": 34 },
    { "id": 625, "firstName": "Garik", "lastName": "Ubank", "age": 79 },
    { "id": 626, "firstName": "Christian", "lastName": "Hockell", "age": 31 },
    { "id": 627, "firstName": "Novelia", "lastName": "Rosen", "age": 57 },
    { "id": 628, "firstName": "Leelah", "lastName": "Eastham", "age": 63 },
    { "id": 629, "firstName": "Faustina", "lastName": "Cornelis", "age": 66 },
    { "id": 630, "firstName": "Marlena", "lastName": "Kernell", "age": 54 },
    { "id": 631, "firstName": "Luella", "lastName": "Chason", "age": 32 },
    { "id": 632, "firstName": "Claudine", "lastName": "Bednell", "age": 60 },
    { "id": 633, "firstName": "Corilla", "lastName": "Vear", "age": 64 },
    { "id": 634, "firstName": "Merissa", "lastName": "Applegarth", "age": 45 },
    { "id": 635, "firstName": "Justus", "lastName": "Buswell", "age": 60 },
    { "id": 636, "firstName": "Joann", "lastName": "Escale", "age": 53 },
    { "id": 637, "firstName": "Reinhold", "lastName": "Samme", "age": 46 },
    { "id": 638, "firstName": "Anya", "lastName": "Triggle", "age": 26 },
    { "id": 639, "firstName": "Alford", "lastName": "Barbrook", "age": 36 },
    { "id": 640, "firstName": "Germain", "lastName": "Lobe", "age": 28 },
    { "id": 641, "firstName": "Jerrylee", "lastName": "Tod", "age": 20 },
    { "id": 642, "firstName": "Base", "lastName": "McKew", "age": 47 },
    { "id": 643, "firstName": "Onfroi", "lastName": "Murton", "age": 34 },
    { "id": 644, "firstName": "Alfredo", "lastName": "Drewell", "age": 34 },
    { "id": 645, "firstName": "Katy", "lastName": "Stanhope", "age": 31 },
    { "id": 646, "firstName": "Donny", "lastName": "Broszkiewicz", "age": 71 },
    { "id": 647, "firstName": "Chrystal", "lastName": "Kobera", "age": 48 },
    { "id": 648, "firstName": "Gus", "lastName": "Spiteri", "age": 57 },
    { "id": 649, "firstName": "Kirbee", "lastName": "Fearne", "age": 44 },
    { "id": 650, "firstName": "Huntlee", "lastName": "Strutt", "age": 21 },
    { "id": 651, "firstName": "Sibylla", "lastName": "Mulcahy", "age": 33 },
    { "id": 652, "firstName": "Lemar", "lastName": "Josland", "age": 42 },
    { "id": 653, "firstName": "Eden", "lastName": "Amar", "age": 24 },
    { "id": 654, "firstName": "Emiline", "lastName": "Crowth", "age": 24 },
    {
      "id": 655,
      "firstName": "Chastity",
      "lastName": "Sonnenschein",
      "age": 74
    },
    { "id": 656, "firstName": "Dall", "lastName": "Coggles", "age": 28 },
    { "id": 657, "firstName": "Joyann", "lastName": "Sievewright", "age": 88 },
    { "id": 658, "firstName": "Sarena", "lastName": "Devlin", "age": 22 },
    { "id": 659, "firstName": "Aprilette", "lastName": "Poat", "age": 35 },
    { "id": 660, "firstName": "Lianne", "lastName": "Phlippi", "age": 53 },
    { "id": 661, "firstName": "Hildagard", "lastName": "Blakes", "age": 28 },
    { "id": 662, "firstName": "Rosamond", "lastName": "Tidey", "age": 63 },
    { "id": 663, "firstName": "Helga", "lastName": "Londesborough", "age": 87 },
    { "id": 664, "firstName": "Sherman", "lastName": "Vermer", "age": 47 },
    { "id": 665, "firstName": "Twyla", "lastName": "Knottley", "age": 23 },
    { "id": 666, "firstName": "Karlee", "lastName": "Top", "age": 49 },
    { "id": 667, "firstName": "Roderich", "lastName": "Willshear", "age": 21 },
    { "id": 668, "firstName": "Brook", "lastName": "Kohring", "age": 58 },
    { "id": 669, "firstName": "Binky", "lastName": "Clendinning", "age": 69 },
    { "id": 670, "firstName": "Tedie", "lastName": "Kyrkeman", "age": 25 },
    { "id": 671, "firstName": "Hayes", "lastName": "Whyborne", "age": 17 },
    { "id": 672, "firstName": "Axel", "lastName": "Tilston", "age": 81 },
    { "id": 673, "firstName": "Marillin", "lastName": "Schimmang", "age": 44 },
    { "id": 674, "firstName": "Bondie", "lastName": "Dossantos", "age": 82 },
    { "id": 675, "firstName": "Con", "lastName": "Stihl", "age": 55 },
    { "id": 676, "firstName": "Beulah", "lastName": "Dullingham", "age": 62 },
    { "id": 677, "firstName": "Eal", "lastName": "Maletratt", "age": 68 },
    { "id": 678, "firstName": "Evelina", "lastName": "Dugald", "age": 40 },
    { "id": 679, "firstName": "Harold", "lastName": "Hallawell", "age": 58 },
    { "id": 680, "firstName": "Arlee", "lastName": "Janacek", "age": 44 },
    { "id": 681, "firstName": "Emmy", "lastName": "Winham", "age": 53 },
    { "id": 682, "firstName": "Latisha", "lastName": "Biagini", "age": 45 },
    { "id": 683, "firstName": "Flss", "lastName": "Petow", "age": 88 },
    { "id": 684, "firstName": "Stacy", "lastName": "Mee", "age": 41 },
    { "id": 685, "firstName": "Izabel", "lastName": "Enefer", "age": 27 },
    { "id": 686, "firstName": "Lorain", "lastName": "Dabney", "age": 85 },
    { "id": 687, "firstName": "Erin", "lastName": "Stroulger", "age": 37 },
    { "id": 688, "firstName": "Fredrick", "lastName": "d' Elboux", "age": 76 },
    { "id": 689, "firstName": "Emmaline", "lastName": "Diviny", "age": 31 },
    { "id": 690, "firstName": "Carver", "lastName": "Staddon", "age": 90 },
    { "id": 691, "firstName": "Joelynn", "lastName": "Chart", "age": 41 },
    { "id": 692, "firstName": "Emmey", "lastName": "Vaillant", "age": 20 },
    { "id": 693, "firstName": "Davey", "lastName": "Dunphie", "age": 37 },
    { "id": 694, "firstName": "Willy", "lastName": "Veysey", "age": 77 },
    { "id": 695, "firstName": "Xever", "lastName": "Frackiewicz", "age": 39 },
    { "id": 696, "firstName": "Marysa", "lastName": "Shinefield", "age": 71 },
    { "id": 697, "firstName": "Waverly", "lastName": "Dever", "age": 29 },
    { "id": 698, "firstName": "Odelinda", "lastName": "Wattisham", "age": 71 },
    { "id": 699, "firstName": "Delmar", "lastName": "Rentelll", "age": 65 },
    { "id": 700, "firstName": "Jeni", "lastName": "Rehor", "age": 87 },
    { "id": 701, "firstName": "Jessie", "lastName": "Viney", "age": 63 },
    { "id": 702, "firstName": "Alwin", "lastName": "Gavin", "age": 16 },
    { "id": 703, "firstName": "Alfi", "lastName": "Lamswood", "age": 24 },
    { "id": 704, "firstName": "Chloette", "lastName": "Crichten", "age": 82 },
    { "id": 705, "firstName": "Kingsley", "lastName": "Edelheit", "age": 39 },
    { "id": 706, "firstName": "Brannon", "lastName": "Lezemore", "age": 89 },
    { "id": 707, "firstName": "Cece", "lastName": "Brazear", "age": 86 },
    { "id": 708, "firstName": "Ilise", "lastName": "Aps", "age": 62 },
    { "id": 709, "firstName": "Edna", "lastName": "Crouse", "age": 56 },
    { "id": 710, "firstName": "Frannie", "lastName": "Abbyss", "age": 25 },
    { "id": 711, "firstName": "Nicholle", "lastName": "Ierland", "age": 75 },
    { "id": 712, "firstName": "Briant", "lastName": "Hindsberg", "age": 70 },
    { "id": 713, "firstName": "Maridel", "lastName": "Oram", "age": 57 },
    { "id": 714, "firstName": "Krishnah", "lastName": "Guidera", "age": 84 },
    { "id": 715, "firstName": "Darell", "lastName": "Lagadu", "age": 78 },
    { "id": 716, "firstName": "Bartlet", "lastName": "Rymmer", "age": 28 },
    { "id": 717, "firstName": "Ella", "lastName": "Guiot", "age": 84 },
    { "id": 718, "firstName": "Marlyn", "lastName": "Romera", "age": 44 },
    { "id": 719, "firstName": "Aluin", "lastName": "Bes", "age": 76 },
    { "id": 720, "firstName": "Ali", "lastName": "Rupert", "age": 70 },
    { "id": 721, "firstName": "Bennie", "lastName": "Drinkall", "age": 69 },
    { "id": 722, "firstName": "Chick", "lastName": "Mullett", "age": 82 },
    { "id": 723, "firstName": "Jobyna", "lastName": "Carless", "age": 61 },
    { "id": 724, "firstName": "Merla", "lastName": "Presswell", "age": 32 },
    { "id": 725, "firstName": "Melody", "lastName": "Gullyes", "age": 17 },
    { "id": 726, "firstName": "Mame", "lastName": "Bertot", "age": 35 },
    { "id": 727, "firstName": "Angelique", "lastName": "Pyford", "age": 71 },
    { "id": 728, "firstName": "Stanfield", "lastName": "Khidr", "age": 75 },
    { "id": 729, "firstName": "Penn", "lastName": "Leach", "age": 89 },
    { "id": 730, "firstName": "Jennette", "lastName": "Gallyhaock", "age": 61 },
    { "id": 731, "firstName": "Rosanne", "lastName": "Stanmer", "age": 47 },
    { "id": 732, "firstName": "Ottilie", "lastName": "Izkovicz", "age": 83 },
    { "id": 733, "firstName": "Clayton", "lastName": "Markie", "age": 69 },
    { "id": 734, "firstName": "Rodi", "lastName": "Neylon", "age": 75 },
    { "id": 735, "firstName": "Pris", "lastName": "Ramalho", "age": 39 },
    { "id": 736, "firstName": "Chickie", "lastName": "Hannond", "age": 55 },
    { "id": 737, "firstName": "Ekaterina", "lastName": "Pomroy", "age": 26 },
    { "id": 738, "firstName": "Modestia", "lastName": "Vedishchev", "age": 57 },
    { "id": 739, "firstName": "Gearalt", "lastName": "Wreiford", "age": 40 },
    { "id": 740, "firstName": "See", "lastName": "Sustins", "age": 51 },
    { "id": 741, "firstName": "Susann", "lastName": "Filippozzi", "age": 62 },
    { "id": 742, "firstName": "Alexandros", "lastName": "Walne", "age": 79 },
    { "id": 743, "firstName": "Katerine", "lastName": "Lait", "age": 79 },
    { "id": 744, "firstName": "Margo", "lastName": "Gilley", "age": 62 },
    { "id": 745, "firstName": "Teresita", "lastName": "Tebbit", "age": 17 },
    { "id": 746, "firstName": "Elfrieda", "lastName": "Parell", "age": 62 },
    { "id": 747, "firstName": "Justinn", "lastName": "Philippet", "age": 86 },
    { "id": 748, "firstName": "Xenia", "lastName": "Pudge", "age": 43 },
    { "id": 749, "firstName": "Elfie", "lastName": "Dignall", "age": 90 },
    { "id": 750, "firstName": "Perry", "lastName": "Nibloe", "age": 36 },
    { "id": 751, "firstName": "Calvin", "lastName": "Summerson", "age": 44 },
    { "id": 752, "firstName": "Julius", "lastName": "Gabby", "age": 29 },
    { "id": 753, "firstName": "Yoshi", "lastName": "McKleod", "age": 62 },
    { "id": 754, "firstName": "Rafael", "lastName": "McNickle", "age": 73 },
    { "id": 755, "firstName": "Minny", "lastName": "Antonomoli", "age": 48 },
    { "id": 756, "firstName": "Abbe", "lastName": "Hawgood", "age": 33 },
    { "id": 757, "firstName": "Al", "lastName": "Harnwell", "age": 60 },
    { "id": 758, "firstName": "Finley", "lastName": "Maclaine", "age": 81 },
    { "id": 759, "firstName": "Sunny", "lastName": "Tinkham", "age": 26 },
    { "id": 760, "firstName": "Keri", "lastName": "Foxten", "age": 45 },
    { "id": 761, "firstName": "Teddy", "lastName": "Doggart", "age": 84 },
    { "id": 762, "firstName": "Grover", "lastName": "Shearston", "age": 87 },
    { "id": 763, "firstName": "Eba", "lastName": "Caze", "age": 81 },
    { "id": 764, "firstName": "Dena", "lastName": "Pods", "age": 62 },
    { "id": 765, "firstName": "Eugen", "lastName": "Whitwham", "age": 55 },
    { "id": 766, "firstName": "Jenda", "lastName": "Quogan", "age": 40 },
    { "id": 767, "firstName": "Douglas", "lastName": "Woodcock", "age": 33 },
    { "id": 768, "firstName": "Raynard", "lastName": "Pendrick", "age": 32 },
    { "id": 769, "firstName": "Pascal", "lastName": "Buick", "age": 35 },
    { "id": 770, "firstName": "Ennis", "lastName": "Bulmer", "age": 89 },
    { "id": 771, "firstName": "Elysee", "lastName": "Lemarie", "age": 34 },
    { "id": 772, "firstName": "Welch", "lastName": "Heiner", "age": 69 },
    { "id": 773, "firstName": "Nalani", "lastName": "Boffey", "age": 79 },
    { "id": 774, "firstName": "Marietta", "lastName": "Doy", "age": 77 },
    { "id": 775, "firstName": "Natasha", "lastName": "Bestman", "age": 75 },
    { "id": 776, "firstName": "Odo", "lastName": "Jaspar", "age": 69 },
    { "id": 777, "firstName": "Clevey", "lastName": "Stacy", "age": 79 },
    { "id": 778, "firstName": "Brittan", "lastName": "McGowan", "age": 17 },
    { "id": 779, "firstName": "Arch", "lastName": "Yankin", "age": 60 },
    { "id": 780, "firstName": "Cleon", "lastName": "Drydale", "age": 72 },
    { "id": 781, "firstName": "Ardath", "lastName": "Alton", "age": 71 },
    { "id": 782, "firstName": "Melva", "lastName": "Baggaley", "age": 90 },
    { "id": 783, "firstName": "Franchot", "lastName": "Kane", "age": 19 },
    { "id": 784, "firstName": "Grant", "lastName": "Linstead", "age": 24 },
    { "id": 785, "firstName": "Simona", "lastName": "Bragginton", "age": 37 },
    { "id": 786, "firstName": "Lenard", "lastName": "Dorgon", "age": 42 },
    { "id": 787, "firstName": "Fiorenze", "lastName": "Clabburn", "age": 73 },
    { "id": 788, "firstName": "Galvin", "lastName": "Yurenin", "age": 61 },
    { "id": 789, "firstName": "Sutherland", "lastName": "Chaters", "age": 61 },
    { "id": 790, "firstName": "Glyn", "lastName": "Baress", "age": 70 },
    { "id": 791, "firstName": "Karleen", "lastName": "Pohlak", "age": 87 },
    { "id": 792, "firstName": "Eda", "lastName": "Paolo", "age": 48 },
    { "id": 793, "firstName": "Rey", "lastName": "Bretland", "age": 83 },
    { "id": 794, "firstName": "Dominica", "lastName": "Sea", "age": 82 },
    { "id": 795, "firstName": "Powell", "lastName": "Audrey", "age": 48 },
    { "id": 796, "firstName": "Reid", "lastName": "Willock", "age": 69 },
    { "id": 797, "firstName": "Bennie", "lastName": "Blumsom", "age": 20 },
    { "id": 798, "firstName": "Valdemar", "lastName": "Sweatland", "age": 90 },
    { "id": 799, "firstName": "Christa", "lastName": "Ferrand", "age": 47 },
    { "id": 800, "firstName": "Shayne", "lastName": "Sterke", "age": 59 },
    { "id": 801, "firstName": "Halimeda", "lastName": "Hartegan", "age": 75 },
    { "id": 802, "firstName": "Mycah", "lastName": "Jannequin", "age": 53 },
    {
      "id": 803,
      "firstName": "Corrinne",
      "lastName": "Veracruysse",
      "age": 75
    },
    { "id": 804, "firstName": "Tony", "lastName": "L'Hommee", "age": 60 },
    { "id": 805, "firstName": "Aubine", "lastName": "Mackerness", "age": 66 },
    { "id": 806, "firstName": "Beniamino", "lastName": "Whiffin", "age": 65 },
    { "id": 807, "firstName": "Trina", "lastName": "Benian", "age": 85 },
    { "id": 808, "firstName": "Thomasin", "lastName": "Morde", "age": 58 },
    { "id": 809, "firstName": "Samuele", "lastName": "Hartas", "age": 21 },
    { "id": 810, "firstName": "Eustace", "lastName": "Garbert", "age": 76 },
    { "id": 811, "firstName": "Kirstin", "lastName": "Ferfulle", "age": 32 },
    { "id": 812, "firstName": "Taddeusz", "lastName": "Ohm", "age": 26 },
    { "id": 813, "firstName": "Ardisj", "lastName": "Edginton", "age": 83 },
    { "id": 814, "firstName": "Chance", "lastName": "Morgan", "age": 26 },
    { "id": 815, "firstName": "Jamaal", "lastName": "Challens", "age": 52 },
    { "id": 816, "firstName": "Lucille", "lastName": "Buxey", "age": 73 },
    { "id": 817, "firstName": "Thaxter", "lastName": "Purcell", "age": 58 },
    { "id": 818, "firstName": "Prudy", "lastName": "Petrishchev", "age": 57 },
    { "id": 819, "firstName": "Tailor", "lastName": "Padefield", "age": 50 },
    { "id": 820, "firstName": "Pincas", "lastName": "Colman", "age": 75 },
    { "id": 821, "firstName": "Coral", "lastName": "L'Episcopio", "age": 50 },
    { "id": 822, "firstName": "Ferd", "lastName": "Goard", "age": 66 },
    { "id": 823, "firstName": "Mark", "lastName": "Abendroth", "age": 81 },
    { "id": 824, "firstName": "Kellie", "lastName": "Stoffers", "age": 89 },
    { "id": 825, "firstName": "Christin", "lastName": "Dougherty", "age": 65 },
    { "id": 826, "firstName": "Meara", "lastName": "Barson", "age": 73 },
    { "id": 827, "firstName": "Tye", "lastName": "Duckett", "age": 25 },
    { "id": 828, "firstName": "Margaret", "lastName": "Gindghill", "age": 39 },
    { "id": 829, "firstName": "Terrye", "lastName": "Gillease", "age": 36 },
    { "id": 830, "firstName": "Marcy", "lastName": "Vina", "age": 57 },
    { "id": 831, "firstName": "Roselle", "lastName": "O'Cahill", "age": 90 },
    { "id": 832, "firstName": "Gordon", "lastName": "Hardie", "age": 60 },
    { "id": 833, "firstName": "Bank", "lastName": "Gravenell", "age": 69 },
    { "id": 834, "firstName": "Halie", "lastName": "Morena", "age": 90 },
    { "id": 835, "firstName": "Felicdad", "lastName": "Greener", "age": 48 },
    { "id": 836, "firstName": "Millicent", "lastName": "Popham", "age": 81 },
    { "id": 837, "firstName": "Sheppard", "lastName": "Mockett", "age": 22 },
    { "id": 838, "firstName": "Holly", "lastName": "Dowdam", "age": 22 },
    { "id": 839, "firstName": "Dominique", "lastName": "Grigore", "age": 73 },
    { "id": 840, "firstName": "Prissie", "lastName": "Winning", "age": 54 },
    { "id": 841, "firstName": "Hephzibah", "lastName": "Geere", "age": 21 },
    { "id": 842, "firstName": "Billye", "lastName": "Russell", "age": 81 },
    { "id": 843, "firstName": "Timothea", "lastName": "Arias", "age": 39 },
    { "id": 844, "firstName": "Ingra", "lastName": "Conaboy", "age": 60 },
    { "id": 845, "firstName": "Kimmie", "lastName": "Cradey", "age": 74 },
    { "id": 846, "firstName": "Glynis", "lastName": "Skehens", "age": 41 },
    { "id": 847, "firstName": "Novelia", "lastName": "Adshad", "age": 73 },
    { "id": 848, "firstName": "Raleigh", "lastName": "Rosenbush", "age": 89 },
    { "id": 849, "firstName": "Gwynne", "lastName": "Tindley", "age": 72 },
    { "id": 850, "firstName": "Annette", "lastName": "Hansana", "age": 73 },
    { "id": 851, "firstName": "Evered", "lastName": "Sheara", "age": 22 },
    { "id": 852, "firstName": "Antonius", "lastName": "Mintoff", "age": 56 },
    { "id": 853, "firstName": "Sammie", "lastName": "Hinksen", "age": 74 },
    { "id": 854, "firstName": "Weylin", "lastName": "Nunnerley", "age": 83 },
    { "id": 855, "firstName": "Kristo", "lastName": "Sparham", "age": 79 },
    { "id": 856, "firstName": "Burke", "lastName": "Brome", "age": 15 },
    { "id": 857, "firstName": "Wynny", "lastName": "Hamil", "age": 82 },
    { "id": 858, "firstName": "Ulla", "lastName": "Benedicto", "age": 42 },
    { "id": 859, "firstName": "Naoma", "lastName": "Eltune", "age": 81 },
    { "id": 860, "firstName": "Milka", "lastName": "Jansie", "age": 86 },
    { "id": 861, "firstName": "Dinny", "lastName": "Wyllie", "age": 87 },
    { "id": 862, "firstName": "Leanora", "lastName": "McCroft", "age": 87 },
    { "id": 863, "firstName": "Madison", "lastName": "Salmoni", "age": 23 },
    { "id": 864, "firstName": "Evy", "lastName": "Bonhan", "age": 78 },
    { "id": 865, "firstName": "Dionne", "lastName": "Humpherston", "age": 63 },
    { "id": 866, "firstName": "Jody", "lastName": "de Guerre", "age": 57 },
    { "id": 867, "firstName": "Roseanna", "lastName": "Hazelhurst", "age": 78 },
    { "id": 868, "firstName": "Amber", "lastName": "Dayne", "age": 30 },
    { "id": 869, "firstName": "Dorolice", "lastName": "Ward", "age": 71 },
    { "id": 870, "firstName": "Justinian", "lastName": "Jurek", "age": 80 },
    { "id": 871, "firstName": "Onfroi", "lastName": "Sealand", "age": 35 },
    { "id": 872, "firstName": "Misty", "lastName": "Perche", "age": 28 },
    { "id": 873, "firstName": "Minne", "lastName": "O'Corren", "age": 78 },
    {
      "id": 874,
      "firstName": "Clementius",
      "lastName": "Harmeston",
      "age": 70
    },
    { "id": 875, "firstName": "Cahra", "lastName": "Dooly", "age": 89 },
    { "id": 876, "firstName": "Ros", "lastName": "Irons", "age": 29 },
    { "id": 877, "firstName": "Morse", "lastName": "Caulkett", "age": 57 },
    { "id": 878, "firstName": "Maisey", "lastName": "Olliar", "age": 56 },
    { "id": 879, "firstName": "Shawna", "lastName": "Carlone", "age": 37 },
    { "id": 880, "firstName": "Gav", "lastName": "Patchett", "age": 20 },
    { "id": 881, "firstName": "Scott", "lastName": "Llewellyn", "age": 51 },
    { "id": 882, "firstName": "Marlin", "lastName": "Losseljong", "age": 43 },
    { "id": 883, "firstName": "Letitia", "lastName": "Whitter", "age": 81 },
    { "id": 884, "firstName": "Arleyne", "lastName": "McIsaac", "age": 85 },
    { "id": 885, "firstName": "Kellyann", "lastName": "Abdy", "age": 28 },
    { "id": 886, "firstName": "Jerry", "lastName": "Caskey", "age": 29 },
    { "id": 887, "firstName": "Candie", "lastName": "des Remedios", "age": 45 },
    { "id": 888, "firstName": "Melba", "lastName": "Jenkin", "age": 82 },
    { "id": 889, "firstName": "Zulema", "lastName": "Restieaux", "age": 23 },
    { "id": 890, "firstName": "Desirae", "lastName": "Climson", "age": 26 },
    { "id": 891, "firstName": "Chrotoem", "lastName": "Canton", "age": 57 },
    { "id": 892, "firstName": "Lonee", "lastName": "Smerdon", "age": 35 },
    { "id": 893, "firstName": "Katrine", "lastName": "Maus", "age": 65 },
    { "id": 894, "firstName": "Hulda", "lastName": "Barnhart", "age": 27 },
    { "id": 895, "firstName": "Cody", "lastName": "Cawsy", "age": 54 },
    { "id": 896, "firstName": "Piggy", "lastName": "Viollet", "age": 60 },
    { "id": 897, "firstName": "Connie", "lastName": "Ganders", "age": 79 },
    { "id": 898, "firstName": "Marcelo", "lastName": "Poppy", "age": 72 },
    { "id": 899, "firstName": "Clementine", "lastName": "Wellman", "age": 61 },
    { "id": 900, "firstName": "Phineas", "lastName": "Allmond", "age": 78 },
    { "id": 901, "firstName": "Barron", "lastName": "Pidwell", "age": 43 },
    { "id": 902, "firstName": "Stephen", "lastName": "Dearn", "age": 41 },
    { "id": 903, "firstName": "Roxy", "lastName": "Simonard", "age": 57 },
    { "id": 904, "firstName": "Perceval", "lastName": "Jenkin", "age": 77 },
    { "id": 905, "firstName": "Berky", "lastName": "Carruthers", "age": 46 },
    { "id": 906, "firstName": "Darci", "lastName": "Newlands", "age": 29 },
    { "id": 907, "firstName": "Danyelle", "lastName": "Daviot", "age": 20 },
    { "id": 908, "firstName": "Alfie", "lastName": "Rowland", "age": 34 },
    { "id": 909, "firstName": "Skyler", "lastName": "Strowther", "age": 27 },
    { "id": 910, "firstName": "Emmit", "lastName": "Cannan", "age": 71 },
    { "id": 911, "firstName": "Pepillo", "lastName": "Mc Faul", "age": 86 },
    { "id": 912, "firstName": "Truman", "lastName": "Griniov", "age": 34 },
    { "id": 913, "firstName": "Corny", "lastName": "McLleese", "age": 75 },
    { "id": 914, "firstName": "Perle", "lastName": "Paddell", "age": 75 },
    { "id": 915, "firstName": "Ollie", "lastName": "Laurisch", "age": 18 },
    { "id": 916, "firstName": "Wilbert", "lastName": "Collie", "age": 68 },
    { "id": 917, "firstName": "Des", "lastName": "Kilduff", "age": 73 },
    { "id": 918, "firstName": "Roslyn", "lastName": "McKnish", "age": 47 },
    { "id": 919, "firstName": "Oswald", "lastName": "Dedam", "age": 16 },
    { "id": 920, "firstName": "Deny", "lastName": "Cogan", "age": 23 },
    { "id": 921, "firstName": "Ingunna", "lastName": "Simkovich", "age": 38 },
    { "id": 922, "firstName": "Dorris", "lastName": "Stringfellow", "age": 35 },
    { "id": 923, "firstName": "Eddy", "lastName": "Alkin", "age": 37 },
    { "id": 924, "firstName": "Elwira", "lastName": "Bawden", "age": 90 },
    { "id": 925, "firstName": "Gabbi", "lastName": "Cranna", "age": 37 },
    { "id": 926, "firstName": "Hughie", "lastName": "Raiston", "age": 72 },
    { "id": 927, "firstName": "Becca", "lastName": "Anstead", "age": 63 },
    { "id": 928, "firstName": "Vevay", "lastName": "Vest", "age": 55 },
    { "id": 929, "firstName": "Waldo", "lastName": "Stuttman", "age": 65 },
    { "id": 930, "firstName": "Enrika", "lastName": "McAw", "age": 61 },
    { "id": 931, "firstName": "Cora", "lastName": "Desouza", "age": 90 },
    { "id": 932, "firstName": "Margo", "lastName": "Januszewski", "age": 57 },
    { "id": 933, "firstName": "Veronike", "lastName": "Nezey", "age": 81 },
    { "id": 934, "firstName": "Horton", "lastName": "Hlavac", "age": 73 },
    { "id": 935, "firstName": "Abdel", "lastName": "Giroldo", "age": 28 },
    { "id": 936, "firstName": "Kimmy", "lastName": "Pesek", "age": 19 },
    { "id": 937, "firstName": "Alli", "lastName": "Matiebe", "age": 20 },
    { "id": 938, "firstName": "Gay", "lastName": "Stammers", "age": 69 },
    { "id": 939, "firstName": "Ashil", "lastName": "Eskriet", "age": 72 },
    { "id": 940, "firstName": "Uriah", "lastName": "Audas", "age": 45 },
    { "id": 941, "firstName": "Ajay", "lastName": "Hennemann", "age": 44 },
    { "id": 942, "firstName": "Robbert", "lastName": "Steely", "age": 40 },
    { "id": 943, "firstName": "Dionisio", "lastName": "Gounod", "age": 51 },
    { "id": 944, "firstName": "Lindsay", "lastName": "Walklett", "age": 36 },
    { "id": 945, "firstName": "Almeria", "lastName": "Flowitt", "age": 78 },
    { "id": 946, "firstName": "Noland", "lastName": "Lassetter", "age": 89 },
    { "id": 947, "firstName": "Jamima", "lastName": "Palfreeman", "age": 48 },
    { "id": 948, "firstName": "Vin", "lastName": "Roy", "age": 55 },
    { "id": 949, "firstName": "Wyatan", "lastName": "Goadbie", "age": 28 },
    { "id": 950, "firstName": "Isac", "lastName": "Haining", "age": 86 },
    { "id": 951, "firstName": "Peggie", "lastName": "Lackemann", "age": 50 },
    { "id": 952, "firstName": "Garreth", "lastName": "Brocket", "age": 37 },
    { "id": 953, "firstName": "Zachery", "lastName": "Jenkin", "age": 49 },
    { "id": 954, "firstName": "Pincus", "lastName": "Macak", "age": 62 },
    { "id": 955, "firstName": "Jannel", "lastName": "Dibdale", "age": 29 },
    { "id": 956, "firstName": "Caren", "lastName": "Gillbee", "age": 52 },
    { "id": 957, "firstName": "Bonni", "lastName": "Bletsor", "age": 50 },
    { "id": 958, "firstName": "Ketty", "lastName": "Hailwood", "age": 60 },
    { "id": 959, "firstName": "Magda", "lastName": "Forsaith", "age": 87 },
    { "id": 960, "firstName": "Leighton", "lastName": "Duigan", "age": 75 },
    { "id": 961, "firstName": "Verge", "lastName": "Delgardo", "age": 62 },
    { "id": 962, "firstName": "Price", "lastName": "Goodsal", "age": 39 },
    { "id": 963, "firstName": "Theresita", "lastName": "Josefsson", "age": 60 },
    {
      "id": 964,
      "firstName": "Isidoro",
      "lastName": "Ivanshintsev",
      "age": 55
    },
    { "id": 965, "firstName": "Arlie", "lastName": "Riddock", "age": 65 },
    { "id": 966, "firstName": "Quintina", "lastName": "Powles", "age": 24 },
    { "id": 967, "firstName": "Linnet", "lastName": "Goad", "age": 15 },
    { "id": 968, "firstName": "Malynda", "lastName": "Lathaye", "age": 49 },
    { "id": 969, "firstName": "Shina", "lastName": "Welbelove", "age": 48 },
    { "id": 970, "firstName": "Zolly", "lastName": "Willas", "age": 66 },
    { "id": 971, "firstName": "Veronica", "lastName": "Freda", "age": 36 },
    { "id": 972, "firstName": "Pietrek", "lastName": "Rydings", "age": 38 },
    { "id": 973, "firstName": "Lebbie", "lastName": "Jeannequin", "age": 62 },
    { "id": 974, "firstName": "Catlin", "lastName": "Felix", "age": 58 },
    { "id": 975, "firstName": "Evan", "lastName": "Nazer", "age": 55 },
    { "id": 976, "firstName": "Carena", "lastName": "Tollady", "age": 69 },
    { "id": 977, "firstName": "Jenni", "lastName": "Straffon", "age": 78 },
    { "id": 978, "firstName": "Rozina", "lastName": "Dunne", "age": 40 },
    { "id": 979, "firstName": "Lyman", "lastName": "Trevethan", "age": 25 },
    { "id": 980, "firstName": "Halley", "lastName": "Binks", "age": 73 },
    { "id": 981, "firstName": "Marcello", "lastName": "MacGauhy", "age": 64 },
    { "id": 982, "firstName": "Prisca", "lastName": "Metzig", "age": 65 },
    { "id": 983, "firstName": "Kimberly", "lastName": "Dunsmuir", "age": 80 },
    { "id": 984, "firstName": "Tuck", "lastName": "Wisdish", "age": 61 },
    { "id": 985, "firstName": "Boris", "lastName": "Burstowe", "age": 42 },
    { "id": 986, "firstName": "Eleonore", "lastName": "Varley", "age": 70 },
    { "id": 987, "firstName": "Alyss", "lastName": "Roylance", "age": 42 },
    { "id": 988, "firstName": "Natal", "lastName": "Creyke", "age": 21 },
    { "id": 989, "firstName": "Dennet", "lastName": "Batalle", "age": 22 },
    { "id": 990, "firstName": "Alverta", "lastName": "Lanfare", "age": 80 },
    { "id": 991, "firstName": "Manuel", "lastName": "Dinkin", "age": 28 },
    { "id": 992, "firstName": "Datha", "lastName": "Drummond", "age": 68 },
    { "id": 993, "firstName": "Quinlan", "lastName": "Ravenscroft", "age": 78 },
    { "id": 994, "firstName": "Trixie", "lastName": "Sedcole", "age": 79 },
    { "id": 995, "firstName": "Lilith", "lastName": "Crowcher", "age": 38 },
    { "id": 996, "firstName": "Keen", "lastName": "Mason", "age": 49 },
    { "id": 997, "firstName": "Jessie", "lastName": "Zelley", "age": 79 },
    {
      "id": 998,
      "firstName": "Marie-jeanne",
      "lastName": "Rauprich",
      "age": 39
    },
    { "id": 999, "firstName": "Adelle", "lastName": "Andriessen", "age": 36 },
    { "id": 1000, "firstName": "Harris", "lastName": "Gadault", "age": 74 }
  ]
}
